modelspec/__init__.py
modelspec/base_types.py
modelspec/utils.py
modelspec-0.3.7.dist-info/licenses/LICENSE
modelspec-0.3.7.dist-info/METADATA
modelspec-0.3.7.dist-info/WHEEL
modelspec-0.3.7.dist-info/top_level.txt
modelspec-0.3.7.dist-info/RECORD
